donotprint/__init__.py
donotprint/donotprint.py
donotprint-1.0.0.dist-info/LICENSE
donotprint-1.0.0.dist-info/METADATA
donotprint-1.0.0.dist-info/WHEEL
donotprint-1.0.0.dist-info/top_level.txt
donotprint-1.0.0.dist-info/RECORD
