Metadata-Version: 2.1
Name: donotprint
Version: 1.0.0
Summary: function print work or not work
Home-page: https://github.com/geng-Max/donotprint
Author: geng_MAX
Author-email: geng_MAX@hotmail.com
Classifier: Programming Language :: Python :: 3
Classifier: License :: OSI Approved :: MIT License
Classifier: Operating System :: OS Independent
Requires-Python: >=3
License-File: LICENSE
